snowflake/snowflake_data_validation/__init__.py
snowflake/snowflake_data_validation/__main__.py
snowflake/snowflake_data_validation/__version__.py
snowflake/snowflake_data_validation/comparison_orchestrator.py
snowflake/snowflake_data_validation/main_cli.py
snowflake/snowflake_data_validation/table_partitioning_strategy.md
snowflake/snowflake_data_validation/common_cli/cli_partitioning.py
snowflake/snowflake_data_validation/configuration/__init__.py
snowflake/snowflake_data_validation/configuration/configuration_loader.py
snowflake/snowflake_data_validation/configuration/singleton.py
snowflake/snowflake_data_validation/configuration/model/configuration_model.py
snowflake/snowflake_data_validation/configuration/model/connection_types.py
snowflake/snowflake_data_validation/configuration/model/logging_configuration.py
snowflake/snowflake_data_validation/configuration/model/table_configuration.py
snowflake/snowflake_data_validation/configuration/model/validation_configuration.py
snowflake/snowflake_data_validation/configuration/model/connections/__init__.py
snowflake/snowflake_data_validation/connector/__init__.py
snowflake/snowflake_data_validation/connector/connector_base.py
snowflake/snowflake_data_validation/connector/connector_factory_base.py
snowflake/snowflake_data_validation/connector/connector_failure_tracker.py
snowflake/snowflake_data_validation/executer/__init__.py
snowflake/snowflake_data_validation/executer/async_generation_executor.py
snowflake/snowflake_data_validation/executer/async_validation_executor.py
snowflake/snowflake_data_validation/executer/base_validation_executor.py
snowflake/snowflake_data_validation/executer/executor_factory.py
snowflake/snowflake_data_validation/executer/extractor_types.py
snowflake/snowflake_data_validation/executer/source_validation_executor.py
snowflake/snowflake_data_validation/executer/sync_validation_executor.py
snowflake/snowflake_data_validation/extractor/__init__.py
snowflake_data_validation-1.1.0.dist-info/METADATA
snowflake_data_validation-1.1.0.dist-info/WHEEL
snowflake_data_validation-1.1.0.dist-info/entry_points.txt
snowflake_data_validation-1.1.0.dist-info/licenses/LICENSE
snowflake_data_validation-1.1.0.dist-info/RECORD
