Metadata-Version: 2.4
Name: snowflake-data-validation
Version: 1.1.0
Summary: Snowflake Data Validation
Project-URL: Bug Tracker, https://github.com/snowflakedb/migrations-data-validation/issues
Project-URL: Source code, https://github.com/snowflakedb/migrations-data-validation/
Author-email: "Snowflake, Inc." <snowflake-python-libraries-dl@snowflake.com>
License: Snowflake Conversion Software Terms
License-File: LICENSE
Keywords: Snowflake,analytics,cloud,data,database,db,validation
Classifier: Development Status :: 4 - Beta
Classifier: Environment :: Console
Classifier: Environment :: Other Environment
Classifier: Intended Audience :: Developers
Classifier: Intended Audience :: Education
Classifier: Intended Audience :: Information Technology
Classifier: Intended Audience :: System Administrators
Classifier: License :: Other/Proprietary License
Classifier: Operating System :: OS Independent
Classifier: Programming Language :: Python :: 3 :: Only
Classifier: Programming Language :: SQL
Classifier: Topic :: Database
Classifier: Topic :: Scientific/Engineering :: Information Analysis
Classifier: Topic :: Software Development
Classifier: Topic :: Software Development :: Libraries
Classifier: Topic :: Software Development :: Libraries :: Application Frameworks
Classifier: Topic :: Software Development :: Libraries :: Python Modules
Requires-Python: >=3.10
Requires-Dist: cryptography>=3.4.0
Requires-Dist: deepdiff>=8.0.0
Requires-Dist: jinja2>=3.1.6
Requires-Dist: pandas>=2.2.3
Requires-Dist: pyarrow>=14.0.0
Requires-Dist: pydantic-yaml>=1.4.0
Requires-Dist: pydantic>=2.0
Requires-Dist: snowflake-connector-python>=4.0.0
Requires-Dist: toml>=0.10.2
Requires-Dist: typer>=0.15.3
Requires-Dist: typing-extensions>=4.13.2
Requires-Dist: urllib3>=2.6.0
Provides-Extra: all
Requires-Dist: coverage>=7.6.7; extra == 'all'
Requires-Dist: deepdiff>=8.0.0; extra == 'all'
Requires-Dist: hatchling>=1.26.3; extra == 'all'
Requires-Dist: pre-commit>=4.0.1; extra == 'all'
Requires-Dist: pyodbc>=5.2.0; extra == 'all'
Requires-Dist: pytest-cov>=6.0.0; extra == 'all'
Requires-Dist: pytest-mock>=3.14.1; extra == 'all'
Requires-Dist: pytest>=8.3.3; extra == 'all'
Requires-Dist: redshift-connector>=2.1.8; extra == 'all'
Requires-Dist: setuptools>=70.0.0; extra == 'all'
Requires-Dist: teradatasql>=17.20.0.0; extra == 'all'
Requires-Dist: twine==6.0.1; extra == 'all'
Provides-Extra: development
Requires-Dist: coverage>=7.6.7; extra == 'development'
Requires-Dist: deepdiff>=8.0.0; extra == 'development'
Requires-Dist: hatchling>=1.26.3; extra == 'development'
Requires-Dist: pre-commit>=4.0.1; extra == 'development'
Requires-Dist: pytest-cov>=6.0.0; extra == 'development'
Requires-Dist: pytest-mock>=3.14.1; extra == 'development'
Requires-Dist: pytest>=8.3.3; extra == 'development'
Requires-Dist: setuptools>=70.0.0; extra == 'development'
Requires-Dist: twine==6.0.1; extra == 'development'
Provides-Extra: redshift
Requires-Dist: redshift-connector>=2.1.8; extra == 'redshift'
Provides-Extra: sqlserver
Requires-Dist: pyodbc>=5.2.0; extra == 'sqlserver'
Provides-Extra: teradata
Requires-Dist: teradatasql>=17.20.0.0; extra == 'teradata'
